[
  {
    "img": "dsc-8640.jpg",
    "title": "Фестиваль на канале RU.TV",
    "date": "2017-07-13",
    "desc": "Description"
  },
  {
    "img": "sandhy-sondoro---indonesia2.jpg",
    "title": "Гран-при выиграл Sandhy Sondoro",
    "date": "2017-07-11",
    "desc": "8, 12 и 14 сентября зрителей Телеканала RU.TV ждут три незабываемых вечера…"
  },
  {
    "img": "img-0813.jpg",
    "title": "Busta Rhymes выступил на Фестивале",
    "date": "2017-07-10",
    "desc": "Busta Rhymes с триумфом выступил на Фестивале «Белые ночи Санкт-Петербурга»…"
  },
  {
    "img": "dsc-8352.jpg",
    "title": "SCORPIONS открыли Фестиваль",
    "date": "2017-07-08",
    "desc": "Сегодня в Санкт-Петербурге в БКЗ «Октябрьский» стартовал юбилейный Международный…"
  },
  {
    "img": "dsc-8640.jpg",
    "title": "Фестиваль на канале RU.TV",
    "date": "2017-07-13",
    "desc": "Description"
  },
  {
    "img": "sandhy-sondoro---indonesia2.jpg",
    "title": "Гран-при выиграл Sandhy Sondoro",
    "date": "2017-07-11",
    "desc": "8, 12 и 14 сентября зрителей Телеканала RU.TV ждут три незабываемых вечера…"
  }
]